AUTHORS
CHANGELOG
LICENSE
MANIFEST.in
README
distribute_setup.py
requirements.txt
setup.py
telenor_web2sms.py
telenor_web2sms.egg-info/PKG-INFO
telenor_web2sms.egg-info/SOURCES.txt
telenor_web2sms.egg-info/dependency_links.txt
telenor_web2sms.egg-info/entry_points.txt
telenor_web2sms.egg-info/not-zip-safe
telenor_web2sms.egg-info/requires.txt
telenor_web2sms.egg-info/top_level.txt