Metadata-Version: 1.0
Name: telenor-web2sms
Version: 1.0.1
Summary: Console app and Python API for sending SMSs through the Telenor WEB2SMS web app
Home-page: https://bitbucket.org/petar/telenor_web2sms
Author: Petar Maric
Author-email: petar.maric@gmail.com
License: BSD
Download-URL: https://bitbucket.org/petar/telenor_web2sms
Platform: any
Classifier: Development Status :: 5 - Production/Stable
Classifier: Environment :: Console
Classifier: Intended Audience :: Developers
Classifier: License :: OSI Approved :: BSD License
Classifier: Operating System :: OS Independent
Classifier: Programming Language :: Python
Classifier: Programming Language :: Python :: 2.6
Classifier: Topic :: Communications
Classifier: Topic :: Utilities
